{
  "display": {
    "icon": {
      "item": "minecraft:potion",
      "nbt": "{CustomPotionColor:3185650}"
    },
    "title": "It! Lemon Ice",
    "description": "Oque é um Lemon Ice?",
    "frame": "task",
    "show_toast": true,
    "announce_to_chat": true,
    "hidden": false
  },
  "parent": "underfabner:explorador_de_cavernas_root",
  "criteria": {
    "pick_up_elytra": {
      "trigger": "minecraft:consume_item",
      "conditions": {
        "item": {
          "items": [
            "minecraft:potion"
          ],
          "nbt": "{display:{Name:'{\"text\":\"It! Lemon Ice\"}'}}"
        }
      }
    }
  },
  "rewards": {
    "experience": 5
  }
}
